huaweicloudsdksfsturbo/__init__.py
huaweicloudsdksfsturbo/v1/__init__.py
huaweicloudsdksfsturbo/v1/sfsturbo_async_client.py
huaweicloudsdksfsturbo/v1/sfsturbo_client.py
huaweicloudsdksfsturbo/v1/model/__init__.py
huaweicloudsdksfsturbo/v1/model/action_progress.py
huaweicloudsdksfsturbo/v1/model/add_active_directory_domain_request.py
huaweicloudsdksfsturbo/v1/model/add_active_directory_domain_request_body.py
huaweicloudsdksfsturbo/v1/model/add_active_directory_domain_response.py
huaweicloudsdksfsturbo/v1/model/auto_export_policy.py
huaweicloudsdksfsturbo/v1/model/batch_add_shared_tags_request.py
huaweicloudsdksfsturbo/v1/model/batch_add_shared_tags_request_body.py
huaweicloudsdksfsturbo/v1/model/batch_add_shared_tags_response.py
huaweicloudsdksfsturbo/v1/model/bss_info.py
huaweicloudsdksfsturbo/v1/model/bss_info_extend.py
huaweicloudsdksfsturbo/v1/model/change_security_group.py
huaweicloudsdksfsturbo/v1/model/change_security_group_request.py
huaweicloudsdksfsturbo/v1/model/change_security_group_request_body.py
huaweicloudsdksfsturbo/v1/model/change_security_group_response.py
huaweicloudsdksfsturbo/v1/model/change_share_charge_mode_request_body.py
huaweicloudsdksfsturbo/v1/model/change_share_charge_mode_v2_request.py
huaweicloudsdksfsturbo/v1/model/change_share_charge_mode_v2_response.py
huaweicloudsdksfsturbo/v1/model/change_share_name_req.py
huaweicloudsdksfsturbo/v1/model/change_share_name_request.py
huaweicloudsdksfsturbo/v1/model/change_share_name_response.py
huaweicloudsdksfsturbo/v1/model/client_ip_info.py
huaweicloudsdksfsturbo/v1/model/config_nas_target.py
huaweicloudsdksfsturbo/v1/model/create_backend_target_request.py
huaweicloudsdksfsturbo/v1/model/create_backend_target_request_body.py
huaweicloudsdksfsturbo/v1/model/create_backend_target_response.py
huaweicloudsdksfsturbo/v1/model/create_fs_dir_quota_request.py
huaweicloudsdksfsturbo/v1/model/create_fs_dir_quota_request_body.py
huaweicloudsdksfsturbo/v1/model/create_fs_dir_quota_response.py
huaweicloudsdksfsturbo-3.1.184.dist-info/METADATA
huaweicloudsdksfsturbo-3.1.184.dist-info/WHEEL
huaweicloudsdksfsturbo-3.1.184.dist-info/licenses/LICENSE
huaweicloudsdksfsturbo-3.1.184.dist-info/RECORD
